{
    "criteria": {
      "requirement": {
        "trigger": "minecraft:item_used_on_block",
        "conditions": {
          "location": {
            "light": {
              "light": {
                "max": 9,
                "min": 9
              }
            },
            "block": {
              "blocks": [
                "minecraft:bell"
              ],
              "state": {
                "attachment": "ceiling"
              }
            }
          }
        }
      }
    },
    "rewards": {
      "function": "soul_poe:ring_lantern"
    }
  }
  